compuglobal/__init__.py
compuglobal/aio.py
compuglobal/aio_screencap.py
compuglobal/errors.py
compuglobal/frame.py
compuglobal/screencap.py
compuglobal-0.2.7.dist-info/LICENSE
compuglobal-0.2.7.dist-info/METADATA
compuglobal-0.2.7.dist-info/WHEEL
compuglobal-0.2.7.dist-info/top_level.txt
compuglobal-0.2.7.dist-info/RECORD
