Metadata-Version: 2.1
Name: compuglobal
Version: 0.2.7
Summary: Python wrapper for the CGHMC API (Frinkiac, Morbotron, Master Of All Science and more!)
Home-page: https://github.com/MitchellAW/CompuGlobal
Author: MitchellAW
Author-email: mitchwoollatt@gmail.com
License: MIT
Keywords: frinkiac,morbotron,master-of-all-science,good-god-lemon,capital-beat-us,the-simpsons,futurama,rick-and-morty,30 rock,west wing,api
Platform: UNKNOWN
Classifier: Intended Audience :: Developers
Classifier: License :: OSI Approved :: MIT License
Classifier: Programming Language :: Python :: 3.6
Classifier: Programming Language :: Python :: 3.7
Classifier: Programming Language :: Python :: 3.8
Classifier: Programming Language :: Python :: 3.9
Classifier: Programming Language :: Python :: 3.10
License-File: LICENSE
Requires-Dist: requests (>=2.20.0)
Requires-Dist: aiohttp (<4,>=3.6.0)
